{
  "datasets": [
    {
      "name": "45dd0c83",
      "displayName": "demo_spike_dataset",
      "queryLines": [
        "SELECT * FROM main.default.demo_spike_dataset"
      ]
    }
  ],
  "pages": [
    {
      "name": "fa8ef993",
      "displayName": "dashboard",
      "layout": [
        {
          "widget": {
            "name": "301afd7d",
            "queries": [
              {
                "name": "main_query",
                "query": {
                  "datasetName": "45dd0c83",
                  "fields": [
                    {
                      "name": "Date",
                      "expression": "`Date`"
                    },
                    {
                      "name": "sum(Total Orders)",
                      "expression": "SUM(`Total Orders`)"
                    }
                  ],
                  "disaggregated": false
                }
              }
            ],
            "spec": {
              "version": 3,
              "frame": {
                "title": "Total Orders per Date",
                "showTitle": true
              },
              "mark": {
                "colors": [
                  {
                    "themeColorType": "visualizationColors",
                    "position": 4
                  },
                  {
                    "themeColorType": "visualizationColors",
                    "position": 2
                  },
                  {
                    "themeColorType": "visualizationColors",
                    "position": 3
                  },
                  {
                    "themeColorType": "visualizationColors",
                    "position": 4
                  },
                  {
                    "themeColorType": "visualizationColors",
                    "position": 5
                  },
                  {
                    "themeColorType": "visualizationColors",
                    "position": 6
                  },
                  {
                    "themeColorType": "visualizationColors",
                    "position": 7
                  },
                  {
                    "themeColorType": "visualizationColors",
                    "position": 8
                  },
                  {
                    "themeColorType": "visualizationColors",
                    "position": 9
                  },
                  {
                    "themeColorType": "visualizationColors",
                    "position": 10
                  }
                ],
                "size": 2
              },
              "widgetType": "line",
              "encodings": {
                "x": {
                  "fieldName": "Date",
                  "displayName": "Date",
                  "scale": {
                    "type": "temporal"
                  }
                },
                "y": {
                  "fieldName": "sum(Total Orders)",
                  "displayName": "Total Orders",
                  "scale": {
                    "type": "quantitative"
                  }
                }
              }
            }
          },
          "position": {
            "x": 0,
            "y": 0,
            "width": 12,
            "height": 9
          }
        },
        {
          "widget": {
            "name": "feef3893",
            "multilineTextboxSpec": {
              "lines": [
                "Explain the spike on 2026-01-08 in Total Orders."
              ]
            }
          },
          "position": {
            "x": 0,
            "y": 9,
            "width": 3,
            "height": 1
          }
        }
      ],
      "pageType": "PAGE_TYPE_CANVAS",
      "layoutVersion": "GRID_V1"
    }
  ],
  "uiSettings": {
    "theme": {
      "widgetHeaderAlignment": "ALIGNMENT_UNSPECIFIED"
    },
    "applyModeEnabled": false
  }
}
